{"guide_concept.md":"DnqZxMrY","guide_other_donation.md":"D0TzqsiE","guide_other_donation_list.md":"CgrRhcTJ","guide_other_thanks.md":"kj_JUjSf","guide_setup-runtime_android-copy-backup.md":"BWrnXAg0","guide_setup-runtime_android-copy-root.md":"8AcdTjlx","guide_setup-runtime_android-copy.md":"BEzRXnOx","guide_setup-runtime_docker.md":"BStbGl6T","guide_setup-runtime_explain.md":"TChFCw18","guide_setup-runtime_github-down-repo.md":"s7aEl9hZ","guide_setup-runtime_java.md":"CeBmw18S","guide_setup-runtime_nodejs-dependencies.md":"2E9pbnpR","guide_setup-runtime_nodejs-start.md":"CLZAOS-f","guide_setup-runtime_nodejs.md":"C2WDcD8u","guide_setup-runtime_php.md":"DFKTcMkf","guide_setup-runtime_python.md":"CecZuiRP","guide_setup-runtime_q_a-detail_cannot-find-module.md":"rxM5COGA","guide_setup-runtime_q_a.md":"BGpUNWMV","guide_setup-runtime_snippets_open_cmd.md":"CD7YAAWi","guide_tools_github_visit.md":"B051lK2y","guide_tools_wechat_calc-wechat-key.md":"QaZQ5xhd","guide_use_begin.md":"BDuypsxk","guide_use_data.md":"DC6QM7PL","guide_use_draft.md":"D-DMiIng","guide_use_get.md":"BpV64ISv","guide_use_merger.md":"DzctwPSI","guide_use_msg_custom.md":"1A2Zp9_9","guide_use_msg_other_emotion.md":"DUW7mRfj","guide_use_msg_schema.md":"G9wcMXhF","guide_use_msg_template_index.md":"BmoKnHar","guide_use_show.md":"DxklTj98","guide_what-is.md":"Bqpv7fH1","index.md":"BlEh5bpa"}
