{"guide_use_msg_other_emotion.md":"608fd79b","guide_use_show.md":"e0fd3596","guide_what-is.md":"cc9e97c3","index.md":"c2fb9a54","guide_setup-runtime_snippets_open_cmd.md":"f2c90690","guide_concept.md":"7129b6fc","guide_other_donation.md":"01d0728d","guide_other_thanks.md":"ff26b7db","guide_setup-runtime_nodejs.md":"9d912475","guide_setup-runtime_php.md":"dd643096","guide_setup-runtime_java.md":"5ca6165c","guide_other_donation_list.md":"c5bc1a9e","guide_setup-runtime_docker.md":"383315d2","guide_setup-runtime_python.md":"6ba582c8","guide_use_msg_custom.md":"dd3ced44","guide_use_msg_template_index.md":"32e9ca9a","guide_use_get.md":"6e5630f4","guide_use_msg_schema.md":"09f42709","guide_use_merger.md":"10b6056b","guide_use_data.md":"b8f2cdba"}
